tmx2bam/__init__.py
panda3d_tmx2bam-0.0.251.dist-info/LICENSE.md
panda3d_tmx2bam-0.0.251.dist-info/METADATA
panda3d_tmx2bam-0.0.251.dist-info/WHEEL
panda3d_tmx2bam-0.0.251.dist-info/entry_points.txt
panda3d_tmx2bam-0.0.251.dist-info/top_level.txt
panda3d_tmx2bam-0.0.251.dist-info/RECORD
