Metadata-Version: 2.1
Name: panda3d-tmx2bam
Version: 0.0.251
Summary: CLI tool for converting Tiled TMX files to Panda3D BAM files.
Home-page: https://github.com/janentikan/tmx2bam
Author: janEntikan
Author-email: bandaibandai@rocketship.com
License: UNKNOWN
Platform: UNKNOWN
Classifier: Programming Language :: Python :: 3
Classifier: License :: CC0 1.0 Universal (CC0 1.0) Public Domain Dedication
Classifier: Operating System :: OS Independent
Requires-Dist: panda3d
